{
  "Attraction": {"sql": "SELECT * FROM traveldb.`vw_/dashboard/product/accommodation` WHERE UserID=? AND IF (? is null ,- 1, Status) = IF (? is null ,-1, IF(?='released',2,1)) LIMIT ?, ?;",	"params":["UserID","filter","filter","filter","pagestart","pagesize"]},
  "Counts": {"sql": "SELECT ceil(count(*)/ 8) as Count FROM traveldb.`vw_/dashboard/product/accommodation` where  UserID=? AND IF (? is null ,- 1, Status) = IF (? is null ,-1, IF(?='released',2,1));",	"params":["UserID","filter","filter","filter"]}
}